labda/__init__.py
labda/py.typed
labda/validation.py
labda/accelerometers/__init__.py
labda/accelerometers/intensity/__init__.py
labda/accelerometers/intensity/acceleration.py
labda/accelerometers/intensity/counts.py
labda/accelerometers/intensity/intensity.py
labda/accelerometers/intensity/vilpa.py
labda/accelerometers/metrics/__init__.py
labda/accelerometers/metrics/counts.py
labda/accelerometers/metrics/enmo.py
labda/accelerometers/metrics/mad.py
labda/accelerometers/metrics/metrics.py
labda/accelerometers/preprocessing/__init__.py
labda/accelerometers/preprocessing/calibration.py
labda/accelerometers/preprocessing/wear.py
labda/core/__init__.py
labda/core/bouts.py
labda/core/contexts.py
labda/core/expander.py
labda/core/exposures.py
labda/core/filter.py
labda/core/merger.py
labda/core/resampler.py
labda/core/sampling_frequency.py
labda/core/utils.py
labda/core/wear.py
labda/parsers/__init__.py
labda/parsers/actigraph.py
labda/parsers/axivity.py
labda/parsers/palms.py
labda/parsers/parser.py
labda/parsers/qstarz.py
labda/parsers/traccar.py
labda/parsers/sens/__init__.py
labda/parsers/sens/api.py
labda/parsers/sens/file.py
labda/spatial/__init__.py
labda/spatial/estimater.py
labda/spatial/events.py
labda/spatial/expander.py
labda/spatial/filter.py
labda/spatial/imputation.py
labda/spatial/indoor.py
labda/spatial/map.py
labda/spatial/preprocess.py
labda/spatial/st_dbscan.py
labda/spatial/transport.py
labda/spatial/trips.py
labda/spatial/utils.py
labda/surveys/__init__.py
labda/surveys/indicators/__init__.py
labda/surveys/indicators/indicators.py
labda/surveys/indicators/who_bmi_z_score.parquet
labda/surveys/kidscreen/__init__.py
labda/surveys/kidscreen/kidscreen.py
labda/surveys/kidscreen/kidscreen27.py
labda/surveys/pedsql/__init__.py
labda/surveys/pedsql/pedsql.py
labda/surveys/pedsql/pedsql4.py
labda-0.1.0.dist-info/METADATA
labda-0.1.0.dist-info/WHEEL
labda-0.1.0.dist-info/licenses/LICENSE
labda-0.1.0.dist-info/RECORD
