Metadata-Version: 2.4
Name: labda
Version: 0.1.0
Summary: A Python package built for health researchers, transforms raw movement data into compelling stories about human behaviour.
Project-URL: Homepage, https://labda.josefheidler.cz
Project-URL: Documentation, https://labda.josefheidler.cz
Project-URL: Source, https://github.com/josefheidler/labda
Project-URL: Changelog, https://github.com/josefheidler/labda/blob/main/CHANGELOG.md
Author-email: Josef Heidler <jheidler@health.sdu.dk>
License-Expression: BSD-3-Clause
License-File: LICENSE
Keywords: accelerometers,gnss,gps,movement-behavior,physical-activity,sedentary-behaviour,transportation,wearables
Classifier: Intended Audience :: Education
Classifier: Intended Audience :: Science/Research
Classifier: Operating System :: OS Independent
Classifier: Programming Language :: Python
Classifier: Programming Language :: Python :: 3
Classifier: Programming Language :: Python :: 3 :: Only
Classifier: Programming Language :: Python :: 3.11
Classifier: Programming Language :: Python :: 3.12
Classifier: Topic :: Scientific/Engineering
Requires-Python: >=3.11
Requires-Dist: agcounts>=0.2.6
Requires-Dist: altair>=5.5.0
Requires-Dist: colorcet>=3.1.0
Requires-Dist: geopandas>=1.1.1
Requires-Dist: httpx>=0.28.1
Requires-Dist: numba>=0.61.2
Requires-Dist: osmnx>=2.0.5
Requires-Dist: pandas>=2.3.1
Requires-Dist: pingouin>=0.5.5
Requires-Dist: pyarrow>=20.0.0
Requires-Dist: pydeck>=0.9.1
Requires-Dist: pygt3x>=0.7.1
Requires-Dist: resampy>=0.4.3
Requires-Dist: rich>=14.2.0
Requires-Dist: scikit-digital-health>=0.17.9
Requires-Dist: timezonefinder>=7.0.2
Requires-Dist: vegafusion[embed]>=2.0.2
Requires-Dist: vl-convert-python>=1.8.0
